deisa/dask/__init__.py
deisa/dask/__version__.py
deisa/dask/bridge.py
deisa/dask/deisa.py
deisa/dask/handshake.py
deisa/dask/py.typed
deisa_dask-0.3.0.dist-info/licenses/LICENSE
deisa_dask-0.3.0.dist-info/METADATA
deisa_dask-0.3.0.dist-info/WHEEL
deisa_dask-0.3.0.dist-info/top_level.txt
deisa_dask-0.3.0.dist-info/RECORD
