Metadata-Version: 2.4
Name: deisa-dask
Version: 0.3.0
Summary: Deisa: Dask-Enabled In Situ Analytics
Home-page: https://github.com/deisa-project/deisa-dask
Author: Benoît Martin
Author-email: bmartin@cea.fr
License: MIT
Project-URL: Bug Reports, https://github.com/deisa-project/deisa-dask/issues
Project-URL: Source, https://github.com/deisa-project/deisa-dask
Keywords: deisa in-situ
Classifier: Programming Language :: Python :: 3.10
Classifier: License :: OSI Approved :: MIT License
Classifier: Operating System :: OS Independent
Classifier: Development Status :: 3 - Alpha
Requires-Python: >=3.10
License-File: LICENSE
Requires-Dist: deisa-core==0.1.0
Requires-Dist: dask
Requires-Dist: distributed
Provides-Extra: test
Requires-Dist: pytest; extra == "test"
Requires-Dist: pytest-xdist; extra == "test"
Requires-Dist: numpy; extra == "test"
Dynamic: author
Dynamic: author-email
Dynamic: classifier
Dynamic: description-content-type
Dynamic: home-page
Dynamic: keywords
Dynamic: license
Dynamic: license-file
Dynamic: project-url
Dynamic: provides-extra
Dynamic: requires-dist
Dynamic: requires-python
Dynamic: summary
